Workbook

Sheet Qualifying Salary
A1: Qualifying Salary
A2: Area | B2: Cost
A3: FHD | B3: 350000
A4: HHD | B4: 300000
A5: LPH | B5: 250000

Sheet Chart 1

Sheet Applicant Details (2)
A1: First Name | B1: Last Name | C1: Housing Community | D1: Basic Salary | E1: Bonuses & allowances | F1: Salary Deduction | G1: Gross Salary | H1: Net Income | I1: Qualifying Salary | J1: Qualifying Status | K1: Bank Loan Amount | L1: Bank Repayment Amount | M1: Credit Card Loan Amount | N1: Credit Card Repayment Amount | O1: Credit Union Loans | P1: Total Loan Payments | Q1: Balance | R1: Approval Status
A2: James | B2: Moses | C2: FHD | D2: 235562 | E2: =(D2*0.025) -> 5889.05 | F2: =IF(D2>80000, D2*8%+10000,0) -> 28844.96 | G2: =SUM(D2,E2) -> 241451.05 | H2: =SUM(G2,F2) -> 270296.01 | I2: =VLOOKUP(C2,'Qualifying Salary'!$A$2:$B$5,2,1) -> 350000 | J2: =IF(D2>I2,"Qualified","Not Qualified") -> Not Qualified | K2: 3456 | L2: =PMT(0.006,60,-K2,0,0) -> 68.759521 | M2: 547 | N2: =PMT(0.004,18,-M2,0,0) -> 31.556727 | O2: 6000 | P2: =SUM(K2:O2) -> 10103.316 | Q2: =P2-H2 -> -260192.69 | R2: =IF(P2>(H2*0.5),"Approved", "Not Approved") -> Not Approved
A3: Sally | B3: Riverwater | C3: FHD | D3: 100000 | E3: =(D3*0.025) -> 2500 | F3: =IF(D3>80000, D3*8%+10000,0) -> 18000 | G3: =SUM(D3,E3) -> 102500 | H3: =SUM(G3,F3) -> 120500 | I3: =VLOOKUP(C3,'Qualifying Salary'!$A$2:$B$5,2,1) -> 350000 | J3: =IF(D3>I3,"Qualified","Not Qualified") -> Not Qualified | K3: 45644 | L3: =PMT(0.006,60,-K3,0,0) -> 908.11909 | M3: 34850 | N3: =PMT(0.004,18,-M3,0,0) -> 2010.5154 | O3: 6000 | P3: =SUM(K3:O3) -> 89412.635 | Q3: =P3-H3 -> -31087.365 | R3: =IF(P3>(H3*0.5),"Approved", "Not Approved") -> Approved
A4: Bart | B4: Politik | C4: FHD | D4: 24653636 | E4: =(D4*0.025) -> 616340.9 | F4: =IF(D4>80000, D4*8%+10000,0) -> 1982290.9 | G4: =SUM(D4,E4) -> 25269977 | H4: =SUM(G4,F4) -> 27252268 | I4: =VLOOKUP(C4,'Qualifying Salary'!$A$2:$B$5,2,1) -> 350000 | J4: =IF(D4>I4,"Qualified","Not Qualified") -> Qualified | K4: 345643 | L4: =PMT(0.006,60,-K4,0,0) -> 6876.8076 | M4: 3673 | N4: =PMT(0.004,18,-M4,0,0) -> 211.89736 | O4: 6000 | P4: =SUM(K4:O4) -> 362404.71 | Q4: =P4-H4 -> -26889863 | R4: =IF(P4>(H4*0.5),"Approved", "Not Approved") -> Not Approved
A5: Dave | B5: Johannes | C5: FHD | D5: 2235266 | E5: =(D5*0.025) -> 55881.65 | F5: =IF(D5>80000, D5*8%+10000,0) -> 188821.28 | G5: =SUM(D5,E5) -> 2291147.6 | H5: =SUM(G5,F5) -> 2479968.9 | I5: =VLOOKUP(C5,'Qualifying Salary'!$A$2:$B$5,2,1) -> 350000 | J5: =IF(D5>I5,"Qualified","Not Qualified") -> Qualified | K5: 345734 | L5: =PMT(0.006,60,-K5,0,0) -> 6878.6182 | M5: 3453 | N5: =PMT(0.004,18,-M5,0,0) -> 199.20544 | O5: 6000 | P5: =SUM(K5:O5) -> 362264.82 | Q5: =P5-H5 -> -2117704.1 | R5: =IF(P5>(H5*0.5),"Approved", "Not Approved") -> Not Approved
A6: May | B6: Molior | C6: FHD | D6: 38042888 | E6: =(D6*0.025) -> 951072.2 | F6: =IF(D6>80000, D6*8%+10000,0) -> 3053431 | G6: =SUM(D6,E6) -> 38993960 | H6: =SUM(G6,F6) -> 42047391 | I6: =VLOOKUP(C6,'Qualifying Salary'!$A$2:$B$5,2,1) -> 350000 | J6: =IF(D6>I6,"Qualified","Not Qualified") -> Qualified | K6: 381101 | L6: =PMT(0.006,60,-K6,0,0) -> 7582.2692 | M6: 360 | N6: =PMT(0.004,18,-M6,0,0) -> 20.768595 | O6: 6004 | P6: =SUM(K6:O6) -> 395068.04 | Q6: =P6-H6 -> -41652323 | R6: =IF(P6>(H6*0.5),"Approved", "Not Approved") -> Not Approved
A7: Kim | B7: Flakeson | C7: FHD | D7: 7911740 | E7: =(D7*0.025) -> 197793.5 | F7: =IF(D7>80000, D7*8%+10000,0) -> 642939.2 | G7: =SUM(D7,E7) -> 8109533.5 | H7: =SUM(G7,F7) -> 8752472.7 | I7: =VLOOKUP(C7,'Qualifying Salary'!$A$2:$B$5,2,1) -> 350000 | J7: =IF(D7>I7,"Qualified","Not Qualified") -> Qualified | K7: 390404 | L7: =PMT(0.006,60,-K7,0,0) -> 7767.3588 | M7: 363 | N7: =PMT(0.004,18,-M7,0,0) -> 20.941667 | O7: 6007 | P7: =SUM(K7:O7) -> 404562.3 | Q7: =P7-H7 -> -8347910.4 | R7: =IF(P7>(H7*0.5),"Approved", "Not Approved") -> Not Approved
A8: Mark | B8: Davis | C8: FHD | D8: 100000 | E8: =(D8*0.025) -> 2500 | F8: =IF(D8>80000, D8*8%+10000,0) -> 18000 | G8: =SUM(D8,E8) -> 102500 | H8: =SUM(G8,F8) -> 120500 | I8: =VLOOKUP(C8,'Qualifying Salary'!$A$2:$B$5,2,1) -> 350000 | J8: =IF(D8>I8,"Qualified","Not Qualified") -> Not Qualified | K8: 500000 | L8: =PMT(0.006,60,-K8,0,0) -> 9947.8474 | M8: 23423 | N8: =PMT(0.004,18,-M8,0,0) -> 1351.2856 | O8: 6000 | P8: =SUM(K8:O8) -> 540722.13 | Q8: =P8-H8 -> 420222.13 | R8: =IF(P8>(H8*0.5),"Approved", "Not Approved") -> Approved
A9: Leroy | B9: Ham | C9: FHD | D9: 3656846 | E9: =(D9*0.025) -> 91421.15 | F9: =IF(D9>80000, D9*8%+10000,0) -> 302547.68 | G9: =SUM(D9,E9) -> 3748267.1 | H9: =SUM(G9,F9) -> 4050814.8 | I9: =VLOOKUP(C9,'Qualifying Salary'!$A$2:$B$5,2,1) -> 350000 | J9: =IF(D9>I9,"Qualified","Not Qualified") -> Qualified | K9: 526000 | L9: =PMT(0.006,60,-K9,0,0) -> 10465.135 | M9: 35673 | N9: =PMT(0.004,18,-M9,0,0) -> 2057.9947 | O9: 6000 | P9: =SUM(K9:O9) -> 580196.13 | Q9: =P9-H9 -> -3470618.7 | R9: =IF(P9>(H9*0.5),"Approved", "Not Approved") -> Not Approved
A10: Terry | B10: Thompson | C10: FHD | D10: 2037593 | E10: =(D10*0.025) -> 50939.825 | F10: =IF(D10>80000, D10*8%+10000,0) -> 173007.44 | G10: =SUM(D10,E10) -> 2088532.8 | H10: =SUM(G10,F10) -> 2261540.3 | I10: =VLOOKUP(C10,'Qualifying Salary'!$A$2:$B$5,2,1) -> 350000 | J10: =IF(D10>I10,"Qualified","Not Qualified") -> Qualified | K10: 532000 | L10: =PMT(0.006,60,-K10,0,0) -> 10584.51 | M10: 3567 | N10: =PMT(0.004,18,-M10,0,0) -> 205.78217 | O10: 6000 | P10: =SUM(K10:O10) -> 552357.29 | Q10: =P10-H10 -> -1709183 | R10: =IF(P10>(H10*0.5),"Approved", "Not Approved") -> Not Approved
A11: Buios | B11: jone | C11: HHD | D11: 9090000 | E11: =(D11*0.025) -> 227250 | F11: =IF(D11>80000, D11*8%+10000,0) -> 737200 | G11: =SUM(D11,E11) -> 9317250 | H11: =SUM(G11,F11) -> 10054450 | I11: =VLOOKUP(C11,'Qualifying Salary'!$A$2:$B$5,2,1) -> 300000 | J11: =IF(D11>I11,"Qualified","Not Qualified") -> Qualified | K11: 34564 | L11: =PMT(0.006,60,-K11,0,0) -> 687.6748 | M11: 5467 | N11: =PMT(0.004,18,-M11,0,0) -> 315.3942 | O11: 6000 | P11: =SUM(K11:O11) -> 47034.069 | Q11: =P11-H11 -> -10007416 | R11: =IF(P11>(H11*0.5),"Approved", "Not Approved") -> Not Approved
A12: Sue | B12: Jues | C12: HHD | D12: 29352935 | E12: =(D12*0.025) -> 733823.38 | F12: =IF(D12>80000, D12*8%+10000,0) -> 2358234.8 | G12: =SUM(D12,E12) -> 30086758 | H12: =SUM(G12,F12) -> 32444993 | I12: =VLOOKUP(C12,'Qualifying Salary'!$A$2:$B$5,2,1) -> 300000 | J12: =IF(D12>I12,"Qualified","Not Qualified") -> Qualified | K12: 345634 | L12: =PMT(0.006,60,-K12,0,0) -> 6876.6286 | M12: 5673 | N12: =PMT(0.004,18,-M12,0,0) -> 327.27845 | O12: 6000 | P12: =SUM(K12:O12) -> 364510.91 | Q12: =P12-H12 -> -32080482 | R12: =IF(P12>(H12*0.5),"Approved", "Not Approved") -> Not Approved
A13: Berry | B13: Mjar | C13: HHD | D13: 23640770 | E13: =(D13*0.025) -> 591019.25 | F13: =IF(D13>80000, D13*8%+10000,0) -> 1901261.6 | G13: =SUM(D13,E13) -> 24231789 | H13: =SUM(G13,F13) -> 26133051 | I13: =VLOOKUP(C13,'Qualifying Salary'!$A$2:$B$5,2,1) -> 300000 | J13: =IF(D13>I13,"Qualified","Not Qualified") -> Qualified | K13: 374899 | L13: =PMT(0.006,60,-K13,0,0) -> 7458.8761 | M13: 358 | N13: =PMT(0.004,18,-M13,0,0) -> 20.653214 | O13: 6002 | P13: =SUM(K13:O13) -> 388738.53 | Q13: =P13-H13 -> -25744312 | R13: =IF(P13>(H13*0.5),"Approved", "Not Approved") -> Not Approved
... A31: Jamie | B31: Janee | C31: LPH | D31: 9607909 | E31: =(D31*0.025) -> 240197.73 | F31: =IF(D31>80000, D31*8%+10000,0) -> 778632.72 | G31: =SUM(D31,E31) -> 9848106.7 | H31: =SUM(G31,F31) -> 10626739 | I31: =VLOOKUP(C31,'Qualifying Salary'!$A$2:$B$5,2,1) -> 250000 | J31: =IF(D31>I31,"Qualified","Not Qualified") -> Qualified | K31: 402809 | L31: =PMT(0.006,60,-K31,0,0) -> 8014.1649 | M31: 368 | N31: =PMT(0.004,18,-M31,0,0) -> 21.23012 | O31: 6012 | P31: =SUM(K31:O31) -> 417224.4 | Q31: =P31-H31 -> -10209515 | R31: =IF(P31>(H31*0.5),"Approved", "Not Approved") -> Not Approved
D34: FHD | E34: =SUM(H2:H10) -> 87355752
D35: HHD | E35: =SUM(H11:H19) -> 1.4306787e+08
D36: LPH | E36: =SUM(H20:H31) -> 1.3719153e+08

Sheet Applicant Details
A2: First Name | B2: Last Name | C2: Housing Community | D2: Basic Salary | E2: Bonuses & allowances | F2: Salary Deduction | G2: Gross Salary | H2: Net Income | I2: Qualifying Salary | J2: Qualifying Status | K2: Bank Loan Amount | L2: Bank Repayment Amount | M2: Credit Card Loan Amount | N2: Credit Card Repayment Amount | O2: Credit Union Loans | P2: Total Loan Payments | Q2: Approval Status
A3: James | B3: Moses | C3: FHD | D3: 235562 | E3: =(D3*0.025) -> 5889.05 | F3: 100 | G3: =SUM(D3,E3) -> 241451.05 | H3: =SUM(G3,F3) -> 241551.05 | I3: =VLOOKUP(C3,'Qualifying Salary'!$A$2:$B$5,2,1) -> 350000 | J3: =IF(D3>I3,"Qualified","Not Qualified") -> Not Qualified | K3: 3456 | L3: =PMT(0.006,60,-K3,0,0) -> 68.759521 | M3: 547 | N3: =PMT(0.004,18,-M3,0,0) -> 31.556727 | O3: 6000 | P3: =SUM(K3:O3) -> 10103.316 | Q3: =IF(P3>(H3*0.5),"Approved", "Not Approved") -> Not Approved
A4: Sally | B4: Riverwater | C4: FHD | D4: 100000 | E4: =(D4*0.025) -> 2500 | F4: 100 | G4: =SUM(D4,E4) -> 102500 | H4: =SUM(G4,F4) -> 102600 | I4: =VLOOKUP(C4,'Qualifying Salary'!$A$2:$B$5,2,1) -> 350000 | J4: =IF(D4>I4,"Qualified","Not Qualified") -> Not Qualified | K4: 45644 | L4: =PMT(0.006,60,-K4,0,0) -> 908.11909 | M4: 34850 | N4: =PMT(0.004,18,-M4,0,0) -> 2010.5154 | O4: 6000 | P4: =SUM(K4:O4) -> 89412.635 | Q4: =IF(P4>(H4*0.5),"Approved", "Not Approved") -> Approved
A5: Bart | B5: Politik | C5: FHD | D5: 24653636 | E5: =(D5*0.025) -> 616340.9 | F5: 100 | G5: =SUM(D5,E5) -> 25269977 | H5: =SUM(G5,F5) -> 25270077 | I5: =VLOOKUP(C5,'Qualifying Salary'!$A$2:$B$5,2,1) -> 350000 | J5: =IF(D5>I5,"Qualified","Not Qualified") -> Qualified | K5: 345643 | L5: =PMT(0.006,60,-K5,0,0) -> 6876.8076 | M5: 3673 | N5: =PMT(0.004,18,-M5,0,0) -> 211.89736 | O5: 6000 | P5: =SUM(K5:O5) -> 362404.71 | Q5: =IF(P5>(H5*0.5),"Approved", "Not Approved") -> Not Approved
A6: Dave | B6: Johannes | C6: FHD | D6: 2235266 | E6: =(D6*0.025) -> 55881.65 | F6: 100 | G6: =SUM(D6,E6) -> 2291147.6 | H6: =SUM(G6,F6) -> 2291247.6 | I6: =VLOOKUP(C6,'Qualifying Salary'!$A$2:$B$5,2,1) -> 350000 | J6: =IF(D6>I6,"Qualified","Not Qualified") -> Qualified | K6: 345734 | L6: =PMT(0.006,60,-K6,0,0) -> 6878.6182 | M6: 3453 | N6: =PMT(0.004,18,-M6,0,0) -> 199.20544 | O6: 6000 | P6: =SUM(K6:O6) -> 362264.82 | Q6: =IF(P6>(H6*0.5),"Approved", "Not Approved") -> Not Approved
A7: May | B7: Molior | C7: FHD | D7: 38042888 | E7: =(D7*0.025) -> 951072.2 | F7: 100 | G7: =SUM(D7,E7) -> 38993960 | H7: =SUM(G7,F7) -> 38994060 | I7: =VLOOKUP(C7,'Qualifying Salary'!$A$2:$B$5,2,1) -> 350000 | J7: =IF(D7>I7,"Qualified","Not Qualified") -> Qualified | K7: 381101 | L7: =PMT(0.006,60,-K7,0,0) -> 7582.2692 | M7: 360 | N7: =PMT(0.004,18,-M7,0,0) -> 20.768595 | O7: 6004 | P7: =SUM(K7:O7) -> 395068.04 | Q7: =IF(P7>(H7*0.5),"Approved", "Not Approved") -> Not Approved
A8: Kim | B8: Flakeson | C8: FHD | D8: 7911740 | E8: =(D8*0.025) -> 197793.5 | F8: 100 | G8: =SUM(D8,E8) -> 8109533.5 | H8: =SUM(G8,F8) -> 8109633.5 | I8: =VLOOKUP(C8,'Qualifying Salary'!$A$2:$B$5,2,1) -> 350000 | J8: =IF(D8>I8,"Qualified","Not Qualified") -> Qualified | K8: 390404 | L8: =PMT(0.006,60,-K8,0,0) -> 7767.3588 | M8: 363 | N8: =PMT(0.004,18,-M8,0,0) -> 20.941667 | O8: 6007 | P8: =SUM(K8:O8) -> 404562.3 | Q8: =IF(P8>(H8*0.5),"Approved", "Not Approved") -> Not Approved
A9: Mark | B9: Davis | C9: FHD | D9: 100000 | E9: =(D9*0.025) -> 2500 | F9: 100 | G9: =SUM(D9,E9) -> 102500 | H9: =SUM(G9,F9) -> 102600 | I9: =VLOOKUP(C9,'Qualifying Salary'!$A$2:$B$5,2,1) -> 350000 | J9: =IF(D9>I9,"Qualified","Not Qualified") -> Not Qualified | K9: 500000 | L9: =PMT(0.006,60,-K9,0,0) -> 9947.8474 | M9: 23423 | N9: =PMT(0.004,18,-M9,0,0) -> 1351.2856 | O9: 6000 | P9: =SUM(K9:O9) -> 540722.13 | Q9: =IF(P9>(H9*0.5),"Approved", "Not Approved") -> Approved
A10: Leroy | B10: Ham | C10: FHD | D10: 3656846 | E10: =(D10*0.025) -> 91421.15 | F10: 100 | G10: =SUM(D10,E10) -> 3748267.1 | H10: =SUM(G10,F10) -> 3748367.1 | I10: =VLOOKUP(C10,'Qualifying Salary'!$A$2:$B$5,2,1) -> 350000 | J10: =IF(D10>I10,"Qualified","Not Qualified") -> Qualified | K10: 526000 | L10: =PMT(0.006,60,-K10,0,0) -> 10465.135 | M10: 35673 | N10: =PMT(0.004,18,-M10,0,0) -> 2057.9947 | O10: 6000 | P10: =SUM(K10:O10) -> 580196.13 | Q10: =IF(P10>(H10*0.5),"Approved", "Not Approved") -> Not Approved
A11: Terry | B11: Thompson | C11: FHD | D11: 2037593 | E11: =(D11*0.025) -> 50939.825 | F11: 100 | G11: =SUM(D11,E11) -> 2088532.8 | H11: =SUM(G11,F11) -> 2088632.8 | I11: =VLOOKUP(C11,'Qualifying Salary'!$A$2:$B$5,2,1) -> 350000 | J11: =IF(D11>I11,"Qualified","Not Qualified") -> Qualified | K11: 532000 | L11: =PMT(0.006,60,-K11,0,0) -> 10584.51 | M11: 3567 | N11: =PMT(0.004,18,-M11,0,0) -> 205.78217 | O11: 6000 | P11: =SUM(K11:O11) -> 552357.29 | Q11: =IF(P11>(H11*0.5),"Approved", "Not Approved") -> Not Approved
A12: Buios | B12: jone | C12: HHD | D12: 9090000 | E12: =(D12*0.025) -> 227250 | F12: 100 | G12: =SUM(D12,E12) -> 9317250 | H12: =SUM(G12,F12) -> 9317350 | I12: =VLOOKUP(C12,'Qualifying Salary'!$A$2:$B$5,2,1) -> 300000 | J12: =IF(D12>I12,"Qualified","Not Qualified") -> Qualified | K12: 34564 | L12: =PMT(0.006,60,-K12,0,0) -> 687.6748 | M12: 5467 | N12: =PMT(0.004,18,-M12,0,0) -> 315.3942 | O12: 6000 | P12: =SUM(K12:O12) -> 47034.069 | Q12: =IF(P12>(H12*0.5),"Approved", "Not Approved") -> Not Approved
A13: Sue | B13: Jues | C13: HHD | D13: 29352935 | E13: =(D13*0.025) -> 733823.38 | F13: 100 | G13: =SUM(D13,E13) -> 30086758 | H13: =SUM(G13,F13) -> 30086858 | I13: =VLOOKUP(C13,'Qualifying Salary'!$A$2:$B$5,2,1) -> 300000 | J13: =IF(D13>I13,"Qualified","Not Qualified") -> Qualified | K13: 345634 | L13: =PMT(0.006,60,-K13,0,0) -> 6876.6286 | M13: 5673 | N13: =PMT(0.004,18,-M13,0,0) -> 327.27845 | O13: 6000 | P13: =SUM(K13:O13) -> 364510.91 | Q13: =IF(P13>(H13*0.5),"Approved", "Not Approved") -> Not Approved
A14: Berry | B14: Mjar | C14: HHD | D14: 23640770 | E14: =(D14*0.025) -> 591019.25 | F14: 100 | G14: =SUM(D14,E14) -> 24231789 | H14: =SUM(G14,F14) -> 24231889 | I14: =VLOOKUP(C14,'Qualifying Salary'!$A$2:$B$5,2,1) -> 300000 | J14: =IF(D14>I14,"Qualified","Not Qualified") -> Qualified | K14: 374899 | L14: =PMT(0.006,60,-K14,0,0) -> 7458.8761 | M14: 358 | N14: =PMT(0.004,18,-M14,0,0) -> 20.653214 | O14: 6002 | P14: =SUM(K14:O14) -> 388738.53 | Q14: =IF(P14>(H14*0.5),"Approved", "Not Approved") -> Not Approved
... A32: Jamie | B32: Janee | C32: LPH | D32: 9607909 | E32: =(D32*0.025) -> 240197.73 | F32: 101 | G32: =SUM(D32,E32) -> 9848106.7 | H32: =SUM(G32,F32) -> 9848207.7 | I32: =VLOOKUP(C32,'Qualifying Salary'!$A$2:$B$5,2,1) -> 250000 | J32: =IF(D32>I32,"Qualified","Not Qualified") -> Qualified | K32: 402809 | L32: =PMT(0.006,60,-K32,0,0) -> 8014.1649 | M32: 368 | N32: =PMT(0.004,18,-M32,0,0) -> 21.23012 | O32: 6012 | P32: =SUM(K32:O32) -> 417224.4 | Q32: =IF(P32>(H32*0.5),"Approved", "Not Approved") -> Not Approved
D35: FHD | E35: =SUM(H3:H11) -> 80948769
D36: HHD | E36: =SUM(H12:H20) -> 1.3262744e+08
D37: LPH | E37: =SUM(H21:H32) -> 1.27149e+08

Sheet Filtered
A1: First Name | B1: Last Name | C1: Housing Community | D1: Basic Salary | E1: Bonuses & allowances | F1: Gross Salary | G1: Salary Deduction | H1: Net Income | I1: Qualifying Salary | J1: Qualifying Status | K1: Bank Loan Amount | L1: Bank Repayment Amount | M1: Credit Card Loan Amount | N1: Credit Card Repayment Amount | O1: Credit union loans | P1: Total Loan Payments | Q1: Approval Status
A2: {=_xlfn._xlws.filter('Applicant Details'!A3:P31,'Applicant Details'!H3:H31>700000)} -> #NAME? | B2: #NAME? | C2: #NAME? | D2: #NAME? | E2: #NAME? | F2: #NAME? | G2: #NAME? | H2: #NAME? | I2: #NAME? | J2: #NAME? | K2: #NAME? | L2: #NAME? | M2: #NAME? | N2: #NAME? | O2: #NAME? | P2: #NAME?
A3: #NAME? | B3: #NAME? | C3: #NAME? | D3: #NAME? | E3: #NAME? | F3: #NAME? | G3: #NAME? | H3: #NAME? | I3: #NAME? | J3: #NAME? | K3: #NAME? | L3: #NAME? | M3: #NAME? | N3: #NAME? | O3: #NAME? | P3: #NAME?
A4: #NAME? | B4: #NAME? | C4: #NAME? | D4: #NAME? | E4: #NAME? | F4: #NAME? | G4: #NAME? | H4: #NAME? | I4: #NAME? | J4: #NAME? | K4: #NAME? | L4: #NAME? | M4: #NAME? | N4: #NAME? | O4: #NAME? | P4: #NAME?
A5: #NAME? | B5: #NAME? | C5: #NAME? | D5: #NAME? | E5: #NAME? | F5: #NAME? | G5: #NAME? | H5: #NAME? | I5: #NAME? | J5: #NAME? | K5: #NAME? | L5: #NAME? | M5: #NAME? | N5: #NAME? | O5: #NAME? | P5: #NAME?
A6: #NAME? | B6: #NAME? | C6: #NAME? | D6: #NAME? | E6: #NAME? | F6: #NAME? | G6: #NAME? | H6: #NAME? | I6: #NAME? | J6: #NAME? | K6: #NAME? | L6: #NAME? | M6: #NAME? | N6: #NAME? | O6: #NAME? | P6: #NAME?
A7: #NAME? | B7: #NAME? | C7: #NAME? | D7: #NAME? | E7: #NAME? | F7: #NAME? | G7: #NAME? | H7: #NAME? | I7: #NAME? | J7: #NAME? | K7: #NAME? | L7: #NAME? | M7: #NAME? | N7: #NAME? | O7: #NAME? | P7: #NAME?
A8: #NAME? | B8: #NAME? | C8: #NAME? | D8: #NAME? | E8: #NAME? | F8: #NAME? | G8: #NAME? | H8: #NAME? | I8: #NAME? | J8: #NAME? | K8: #NAME? | L8: #NAME? | M8: #NAME? | N8: #NAME? | O8: #NAME? | P8: #NAME?
A9: #NAME? | B9: #NAME? | C9: #NAME? | D9: #NAME? | E9: #NAME? | F9: #NAME? | G9: #NAME? | H9: #NAME? | I9: #NAME? | J9: #NAME? | K9: #NAME? | L9: #NAME? | M9: #NAME? | N9: #NAME? | O9: #NAME? | P9: #NAME?
A10: #NAME? | B10: #NAME? | C10: #NAME? | D10: #NAME? | E10: #NAME? | F10: #NAME? | G10: #NAME? | H10: #NAME? | I10: #NAME? | J10: #NAME? | K10: #NAME? | L10: #NAME? | M10: #NAME? | N10: #NAME? | O10: #NAME? | P10: #NAME?
A11: #NAME? | B11: #NAME? | C11: #NAME? | D11: #NAME? | E11: #NAME? | F11: #NAME? | G11: #NAME? | H11: #NAME? | I11: #NAME? | J11: #NAME? | K11: #NAME? | L11: #NAME? | M11: #NAME? | N11: #NAME? | O11: #NAME? | P11: #NAME?
A12: #NAME? | B12: #NAME? | C12: #NAME? | D12: #NAME? | E12: #NAME? | F12: #NAME? | G12: #NAME? | H12: #NAME? | I12: #NAME? | J12: #NAME? | K12: #NAME? | L12: #NAME? | M12: #NAME? | N12: #NAME? | O12: #NAME? | P12: #NAME?
A13: #NAME? | B13: #NAME? | C13: #NAME? | D13: #NAME? | E13: #NAME? | F13: #NAME? | G13: #NAME? | H13: #NAME? | I13: #NAME? | J13: #NAME? | K13: #NAME? | L13: #NAME? | M13: #NAME? | N13: #NAME? | O13: #NAME? | P13: #NAME?
A14: #NAME? | B14: #NAME? | C14: #NAME? | D14: #NAME? | E14: #NAME? | F14: #NAME? | G14: #NAME? | H14: #NAME? | I14: #NAME? | J14: #NAME? | K14: #NAME? | L14: #NAME? | M14: #NAME? | N14: #NAME? | O14: #NAME? | P14: #NAME?
... A23: #NAME? | B23: #NAME? | C23: #NAME? | D23: #NAME? | E23: #NAME? | F23: #NAME? | G23: #NAME? | H23: #NAME? | I23: #NAME? | J23: #NAME? | K23: #NAME? | L23: #NAME? | M23: #NAME? | N23: #NAME? | O23: #NAME? | P23: #NAME?
